nmdc_mcp/__init__.py
nmdc_mcp/__main__.py
nmdc_mcp/aggregation.js
nmdc_mcp/api.py
nmdc_mcp/client.py
nmdc_mcp/constants.py
nmdc_mcp/main.py
nmdc_mcp/tools.py
nmdc_mcp-0.6.0.dist-info/METADATA
nmdc_mcp-0.6.0.dist-info/WHEEL
nmdc_mcp-0.6.0.dist-info/entry_points.txt
nmdc_mcp-0.6.0.dist-info/RECORD
