Metadata-Version: 2.4
Name: nmdc-mcp
Version: 0.6.0
Summary: FastMCP-based tool for writing prompts against data in the NMDC (National Microbiome Data Collaborative) database
Project-URL: Homepage, https://github.com/microbiomedata/nmdc-mcp
Project-URL: Repository, https://github.com/microbiomedata/nmdc-mcp
Project-URL: Bug Tracker, https://github.com/microbiomedata/nmdc-mcp/issues
Project-URL: Documentation, https://github.com/microbiomedata/nmdc-mcp/blob/main/README.md
Project-URL: Changelog, https://github.com/microbiomedata/nmdc-mcp/releases
Author-email: Chris Mungall <cjmungall@lbl.gov>, Mark Andrew Miller <MAM@lbl.gov>, Sujay Patil <spatil@lbl.gov>
License: MIT
Keywords: biosamples,fastmcp,mcp,microbiome,model-context-protocol,nmdc
Classifier: Development Status :: 4 - Beta
Classifier: Intended Audience :: Developers
Classifier: Intended Audience :: Science/Research
Classifier: License :: OSI Approved :: MIT License
Classifier: Operating System :: OS Independent
Classifier: Programming Language :: Python :: 3
Classifier: Programming Language :: Python :: 3.11
Classifier: Programming Language :: Python :: 3.12
Classifier: Topic :: Scientific/Engineering :: Bio-Informatics
Classifier: Topic :: Software Development :: Libraries :: Python Modules
Requires-Python: >=3.11
Requires-Dist: fastmcp>=2.7.1
Requires-Dist: mcp>=1.0.0
Requires-Dist: openai>=1.0.0
Requires-Dist: python-dotenv>=1.0.0
Requires-Dist: requests>=2.32.4
